{
  "openapi": "3.0.1",
  "info": {
    "title": "Housing API",
    "version": "v1"
  },
  "paths": {
    "/api/AcademicEducation": {
      "get": {
        "tags": [
          "AcademicEducation"
        ],
        "responses": {
          "200": {
            "description": "OK"
          }
        }
      },
      "post": {
        "tags": [
          "AcademicEducation"
        ],
        "requestBody": {
          "content": {
            "application/json": {
              "schema": {
                "$ref": "#/components/schemas/AcademicEducationDto"
              }
            },
            "text/json": {
              "schema": {
                "$ref": "#/components/schemas/AcademicEducationDto"
              }
            },
            "application/*+json": {
              "schema": {
                "$ref": "#/components/schemas/AcademicEducationDto"
              }
            }
          }
        },
        "responses": {
          "200": {
            "description": "OK"
          }
        }
      }
    },
    "/api/AcademicEducation/{studentId}": {
      "get": {
        "tags": [
          "AcademicEducation"
        ],
        "parameters": [
          {
            "name": "studentId",
            "in": "path",
            "required": true,
            "schema": {
              "type": "integer",
              "format": "int32"
            }
          }
        ],
        "responses": {
          "200": {
            "description": "OK"
          }
        }
      },
      "put": {
        "tags": [
          "AcademicEducation"
        ],
        "parameters": [
          {
            "name": "studentId",
            "in": "path",
            "required": true,
            "schema": {
              "type": "integer",
              "format": "int32"
            }
          }
        ],
        "requestBody": {
          "content": {
            "application/json": {
              "schema": {
                "$ref": "#/components/schemas/AcademicEducationDto"
              }
            },
            "text/json": {
              "schema": {
                "$ref": "#/components/schemas/AcademicEducationDto"
              }
            },
            "application/*+json": {
              "schema": {
                "$ref": "#/components/schemas/AcademicEducationDto"
              }
            }
          }
        },
        "responses": {
          "200": {
            "description": "OK"
          }
        }
      }
    },
    "/api/admin/applications": {
      "get": {
        "tags": [
          "AdminApplications"
        ],
        "responses": {
          "200": {
            "description": "OK"
          }
        }
      }
    },
    "/api/admin/applications/{applicationId}/details": {
      "get": {
        "tags": [
          "AdminApplications"
        ],
        "parameters": [
          {
            "name": "applicationId",
            "in": "path",
            "required": true,
            "schema": {
              "type": "integer",
              "format": "int32"
            }
          }
        ],
        "responses": {
          "200": {
            "description": "OK"
          }
        }
      }
    },
    "/api/admin/applications/{applicationId}/accept": {
      "post": {
        "tags": [
          "AdminApplications"
        ],
        "parameters": [
          {
            "name": "applicationId",
            "in": "path",
            "required": true,
            "schema": {
              "type": "integer",
              "format": "int32"
            }
          }
        ],
        "responses": {
          "200": {
            "description": "OK"
          }
        }
      }
    },
    "/api/admin/applications/{applicationId}/reject": {
      "post": {
        "tags": [
          "AdminApplications"
        ],
        "parameters": [
          {
            "name": "applicationId",
            "in": "path",
            "required": true,
            "schema": {
              "type": "integer",
              "format": "int32"
            }
          }
        ],
        "responses": {
          "200": {
            "description": "OK"
          }
        }
      }
    },
    "/api/admin/applications/{applicationId}/fees": {
      "post": {
        "tags": [
          "AdminApplications"
        ],
        "parameters": [
          {
            "name": "applicationId",
            "in": "path",
            "required": true,
            "schema": {
              "type": "integer",
              "format": "int32"
            }
          }
        ],
        "requestBody": {
          "content": {
            "application/json": {
              "schema": {
                "$ref": "#/components/schemas/FeesDto"
              }
            },
            "text/json": {
              "schema": {
                "$ref": "#/components/schemas/FeesDto"
              }
            },
            "application/*+json": {
              "schema": {
                "$ref": "#/components/schemas/FeesDto"
              }
            }
          }
        },
        "responses": {
          "200": {
            "description": "OK"
          }
        }
      }
    },
    "/api/admin/applications/{applicationId}/notifications": {
      "post": {
        "tags": [
          "AdminApplications"
        ],
        "parameters": [
          {
            "name": "applicationId",
            "in": "path",
            "required": true,
            "schema": {
              "type": "integer",
              "format": "int32"
            }
          }
        ],
        "requestBody": {
          "content": {
            "application/json": {
              "schema": {
                "$ref": "#/components/schemas/NotificationDto"
              }
            },
            "text/json": {
              "schema": {
                "$ref": "#/components/schemas/NotificationDto"
              }
            },
            "application/*+json": {
              "schema": {
                "$ref": "#/components/schemas/NotificationDto"
              }
            }
          }
        },
        "responses": {
          "200": {
            "description": "OK"
          }
        }
      }
    },
    "/api/admin/complaints/unresolved": {
      "get": {
        "tags": [
          "AdminComplaints"
        ],
        "responses": {
          "200": {
            "description": "OK"
          }
        }
      }
    },
    "/api/admin/complaints/resolve/{complaintId}": {
      "post": {
        "tags": [
          "AdminComplaints"
        ],
        "parameters": [
          {
            "name": "complaintId",
            "in": "path",
            "required": true,
            "schema": {
              "type": "integer",
              "format": "int32"
            }
          }
        ],
        "requestBody": {
          "content": {
            "application/json": {
              "schema": {
                "$ref": "#/components/schemas/ResolveComplaintDto"
              }
            },
            "text/json": {
              "schema": {
                "$ref": "#/components/schemas/ResolveComplaintDto"
              }
            },
            "application/*+json": {
              "schema": {
                "$ref": "#/components/schemas/ResolveComplaintDto"
              }
            }
          }
        },
        "responses": {
          "200": {
            "description": "OK"
          }
        }
      }
    },
    "/api/admin/payments/pending": {
      "get": {
        "tags": [
          "AdminFeePayment"
        ],
        "responses": {
          "200": {
            "description": "OK"
          }
        }
      }
    },
    "/api/admin/payments/approve/{feePaymentId}": {
      "post": {
        "tags": [
          "AdminFeePayment"
        ],
        "parameters": [
          {
            "name": "feePaymentId",
            "in": "path",
            "required": true,
            "schema": {
              "type": "integer",
              "format": "int32"
            }
          }
        ],
        "responses": {
          "200": {
            "description": "OK"
          }
        }
      }
    },
    "/api/admin/payments/reject/{feePaymentId}": {
      "post": {
        "tags": [
          "AdminFeePayment"
        ],
        "parameters": [
          {
            "name": "feePaymentId",
            "in": "path",
            "required": true,
            "schema": {
              "type": "integer",
              "format": "int32"
            }
          }
        ],
        "responses": {
          "200": {
            "description": "OK"
          }
        }
      }
    },
    "/api/admin/housing-fees/set-global": {
      "post": {
        "tags": [
          "AdminHousingFees"
        ],
        "parameters": [
          {
            "name": "amount",
            "in": "query",
            "schema": {
              "type": "number",
              "format": "double"
            }
          },
          {
            "name": "notes",
            "in": "query",
            "schema": {
              "type": "string"
            }
          }
        ],
        "responses": {
          "200": {
            "description": "OK"
          }
        }
      }
    },
    "/api/admin/housing-fees": {
      "get": {
        "tags": [
          "AdminHousingFees"
        ],
        "responses": {
          "200": {
            "description": "OK"
          }
        }
      }
    },
    "/api/admin/housing-fees/student/{studentId}": {
      "get": {
        "tags": [
          "AdminHousingFees"
        ],
        "parameters": [
          {
            "name": "studentId",
            "in": "path",
            "required": true,
            "schema": {
              "type": "integer",
              "format": "int32"
            }
          }
        ],
        "responses": {
          "200": {
            "description": "OK"
          }
        }
      }
    },
    "/api/admin/housing-fees/{id}": {
      "put": {
        "tags": [
          "AdminHousingFees"
        ],
        "parameters": [
          {
            "name": "id",
            "in": "path",
            "required": true,
            "schema": {
              "type": "integer",
              "format": "int32"
            }
          }
        ],
        "requestBody": {
          "content": {
            "application/json": {
              "schema": {
                "type": "number",
                "format": "double"
              }
            },
            "text/json": {
              "schema": {
                "type": "number",
                "format": "double"
              }
            },
            "application/*+json": {
              "schema": {
                "type": "number",
                "format": "double"
              }
            }
          }
        },
        "responses": {
          "200": {
            "description": "OK"
          }
        }
      },
      "delete": {
        "tags": [
          "AdminHousingFees"
        ],
        "parameters": [
          {
            "name": "id",
            "in": "path",
            "required": true,
            "schema": {
              "type": "integer",
              "format": "int32"
            }
          }
        ],
        "responses": {
          "200": {
            "description": "OK"
          }
        }
      }
    },
    "/api/admin/housing-fees/{id}/mark-paid": {
      "put": {
        "tags": [
          "AdminHousingFees"
        ],
        "parameters": [
          {
            "name": "id",
            "in": "path",
            "required": true,
            "schema": {
              "type": "integer",
              "format": "int32"
            }
          }
        ],
        "responses": {
          "200": {
            "description": "OK"
          }
        }
      }
    },
    "/api/admin/notifications/send-to-all": {
      "post": {
        "tags": [
          "AdminNotification"
        ],
        "requestBody": {
          "content": {
            "application/json": {
              "schema": {
                "$ref": "#/components/schemas/NotificationDto"
              }
            },
            "text/json": {
              "schema": {
                "$ref": "#/components/schemas/NotificationDto"
              }
            },
            "application/*+json": {
              "schema": {
                "$ref": "#/components/schemas/NotificationDto"
              }
            }
          }
        },
        "responses": {
          "200": {
            "description": "OK"
          }
        }
      }
    },
    "/api/admin/application-statuses": {
      "get": {
        "tags": [
          "ApplicationStatus"
        ],
        "responses": {
          "200": {
            "description": "OK"
          }
        }
      },
      "post": {
        "tags": [
          "ApplicationStatus"
        ],
        "requestBody": {
          "content": {
            "application/json": {
              "schema": {
                "$ref": "#/components/schemas/ApplicationStatusDto"
              }
            },
            "text/json": {
              "schema": {
                "$ref": "#/components/schemas/ApplicationStatusDto"
              }
            },
            "application/*+json": {
              "schema": {
                "$ref": "#/components/schemas/ApplicationStatusDto"
              }
            }
          }
        },
        "responses": {
          "200": {
            "description": "OK"
          }
        }
      }
    },
    "/api/admin/application-statuses/{id}": {
      "get": {
        "tags": [
          "ApplicationStatus"
        ],
        "parameters": [
          {
            "name": "id",
            "in": "path",
            "required": true,
            "schema": {
              "type": "integer",
              "format": "int32"
            }
          }
        ],
        "responses": {
          "200": {
            "description": "OK"
          }
        }
      },
      "put": {
        "tags": [
          "ApplicationStatus"
        ],
        "parameters": [
          {
            "name": "id",
            "in": "path",
            "required": true,
            "schema": {
              "type": "integer",
              "format": "int32"
            }
          }
        ],
        "requestBody": {
          "content": {
            "application/json": {
              "schema": {
                "$ref": "#/components/schemas/ApplicationStatusDto"
              }
            },
            "text/json": {
              "schema": {
                "$ref": "#/components/schemas/ApplicationStatusDto"
              }
            },
            "application/*+json": {
              "schema": {
                "$ref": "#/components/schemas/ApplicationStatusDto"
              }
            }
          }
        },
        "responses": {
          "200": {
            "description": "OK"
          }
        }
      },
      "delete": {
        "tags": [
          "ApplicationStatus"
        ],
        "parameters": [
          {
            "name": "id",
            "in": "path",
            "required": true,
            "schema": {
              "type": "integer",
              "format": "int32"
            }
          }
        ],
        "responses": {
          "200": {
            "description": "OK"
          }
        }
      }
    },
    "/api/admin/application-windows": {
      "get": {
        "tags": [
          "ApplicationWindow"
        ],
        "responses": {
          "200": {
            "description": "OK"
          }
        }
      },
      "post": {
        "tags": [
          "ApplicationWindow"
        ],
        "requestBody": {
          "content": {
            "application/json": {
              "schema": {
                "$ref": "#/components/schemas/ApplicationWindowDto"
              }
            },
            "text/json": {
              "schema": {
                "$ref": "#/components/schemas/ApplicationWindowDto"
              }
            },
            "application/*+json": {
              "schema": {
                "$ref": "#/components/schemas/ApplicationWindowDto"
              }
            }
          }
        },
        "responses": {
          "200": {
            "description": "OK"
          }
        }
      }
    },
    "/api/admin/application-windows/{id}": {
      "get": {
        "tags": [
          "ApplicationWindow"
        ],
        "parameters": [
          {
            "name": "id",
            "in": "path",
            "required": true,
            "schema": {
              "type": "integer",
              "format": "int32"
            }
          }
        ],
        "responses": {
          "200": {
            "description": "OK"
          }
        }
      },
      "put": {
        "tags": [
          "ApplicationWindow"
        ],
        "parameters": [
          {
            "name": "id",
            "in": "path",
            "required": true,
            "schema": {
              "type": "integer",
              "format": "int32"
            }
          }
        ],
        "requestBody": {
          "content": {
            "application/json": {
              "schema": {
                "$ref": "#/components/schemas/ApplicationWindowDto"
              }
            },
            "text/json": {
              "schema": {
                "$ref": "#/components/schemas/ApplicationWindowDto"
              }
            },
            "application/*+json": {
              "schema": {
                "$ref": "#/components/schemas/ApplicationWindowDto"
              }
            }
          }
        },
        "responses": {
          "200": {
            "description": "OK"
          }
        }
      },
      "delete": {
        "tags": [
          "ApplicationWindow"
        ],
        "parameters": [
          {
            "name": "id",
            "in": "path",
            "required": true,
            "schema": {
              "type": "integer",
              "format": "int32"
            }
          }
        ],
        "responses": {
          "200": {
            "description": "OK"
          }
        }
      }
    },
    "/api/admin/application-windows/active": {
      "get": {
        "tags": [
          "ApplicationWindow"
        ],
        "responses": {
          "200": {
            "description": "OK"
          }
        }
      }
    },
    "/api/auth/login": {
      "post": {
        "tags": [
          "Auth"
        ],
        "requestBody": {
          "content": {
            "application/json": {
              "schema": {
                "$ref": "#/components/schemas/LoginDto"
              }
            },
            "text/json": {
              "schema": {
                "$ref": "#/components/schemas/LoginDto"
              }
            },
            "application/*+json": {
              "schema": {
                "$ref": "#/components/schemas/LoginDto"
              }
            }
          }
        },
        "responses": {
          "200": {
            "description": "OK"
          }
        }
      }
    },
    "/api/auth/create-admin": {
      "post": {
        "tags": [
          "Auth"
        ],
        "requestBody": {
          "content": {
            "application/json": {
              "schema": {
                "$ref": "#/components/schemas/RegisterDto"
              }
            },
            "text/json": {
              "schema": {
                "$ref": "#/components/schemas/RegisterDto"
              }
            },
            "application/*+json": {
              "schema": {
                "$ref": "#/components/schemas/RegisterDto"
              }
            }
          }
        },
        "responses": {
          "200": {
            "description": "OK"
          }
        }
      }
    },
    "/api/admin/base-housing-fees/set-global": {
      "post": {
        "tags": [
          "BaseHousingFees"
        ],
        "parameters": [
          {
            "name": "amount",
            "in": "query",
            "schema": {
              "type": "number",
              "format": "double"
            }
          },
          {
            "name": "notes",
            "in": "query",
            "schema": {
              "type": "string"
            }
          }
        ],
        "responses": {
          "200": {
            "description": "OK"
          }
        }
      }
    },
    "/api/admin/base-housing-fees/update-global": {
      "put": {
        "tags": [
          "BaseHousingFees"
        ],
        "parameters": [
          {
            "name": "newAmount",
            "in": "query",
            "schema": {
              "type": "number",
              "format": "double"
            }
          }
        ],
        "responses": {
          "200": {
            "description": "OK"
          }
        }
      }
    },
    "/api/admin/base-housing-fees": {
      "get": {
        "tags": [
          "BaseHousingFees"
        ],
        "responses": {
          "200": {
            "description": "OK"
          }
        }
      }
    },
    "/api/admin/base-housing-fees/{id}": {
      "delete": {
        "tags": [
          "BaseHousingFees"
        ],
        "parameters": [
          {
            "name": "id",
            "in": "path",
            "required": true,
            "schema": {
              "type": "integer",
              "format": "int32"
            }
          }
        ],
        "responses": {
          "200": {
            "description": "OK"
          }
        }
      }
    },
    "/api/Building": {
      "get": {
        "tags": [
          "Building"
        ],
        "responses": {
          "200": {
            "description": "OK"
          }
        }
      },
      "post": {
        "tags": [
          "Building"
        ],
        "requestBody": {
          "content": {
            "application/json": {
              "schema": {
                "$ref": "#/components/schemas/BuildingDto"
              }
            },
            "text/json": {
              "schema": {
                "$ref": "#/components/schemas/BuildingDto"
              }
            },
            "application/*+json": {
              "schema": {
                "$ref": "#/components/schemas/BuildingDto"
              }
            }
          }
        },
        "responses": {
          "200": {
            "description": "OK"
          }
        }
      }
    },
    "/api/Building/{id}": {
      "get": {
        "tags": [
          "Building"
        ],
        "parameters": [
          {
            "name": "id",
            "in": "path",
            "required": true,
            "schema": {
              "type": "integer",
              "format": "int32"
            }
          }
        ],
        "responses": {
          "200": {
            "description": "OK"
          }
        }
      },
      "put": {
        "tags": [
          "Building"
        ],
        "parameters": [
          {
            "name": "id",
            "in": "path",
            "required": true,
            "schema": {
              "type": "integer",
              "format": "int32"
            }
          }
        ],
        "requestBody": {
          "content": {
            "application/json": {
              "schema": {
                "$ref": "#/components/schemas/BuildingDto"
              }
            },
            "text/json": {
              "schema": {
                "$ref": "#/components/schemas/BuildingDto"
              }
            },
            "application/*+json": {
              "schema": {
                "$ref": "#/components/schemas/BuildingDto"
              }
            }
          }
        },
        "responses": {
          "200": {
            "description": "OK"
          }
        }
      },
      "delete": {
        "tags": [
          "Building"
        ],
        "parameters": [
          {
            "name": "id",
            "in": "path",
            "required": true,
            "schema": {
              "type": "integer",
              "format": "int32"
            }
          }
        ],
        "responses": {
          "200": {
            "description": "OK"
          }
        }
      }
    },
    "/api/FamilyContact": {
      "get": {
        "tags": [
          "FamilyContact"
        ],
        "responses": {
          "200": {
            "description": "OK"
          }
        }
      },
      "post": {
        "tags": [
          "FamilyContact"
        ],
        "requestBody": {
          "content": {
            "application/json": {
              "schema": {
                "$ref": "#/components/schemas/FamilyContactDto"
              }
            },
            "text/json": {
              "schema": {
                "$ref": "#/components/schemas/FamilyContactDto"
              }
            },
            "application/*+json": {
              "schema": {
                "$ref": "#/components/schemas/FamilyContactDto"
              }
            }
          }
        },
        "responses": {
          "200": {
            "description": "OK"
          }
        }
      }
    },
    "/api/FamilyContact/{id}": {
      "get": {
        "tags": [
          "FamilyContact"
        ],
        "parameters": [
          {
            "name": "id",
            "in": "path",
            "required": true,
            "schema": {
              "type": "integer",
              "format": "int32"
            }
          }
        ],
        "responses": {
          "200": {
            "description": "OK"
          }
        }
      },
      "put": {
        "tags": [
          "FamilyContact"
        ],
        "parameters": [
          {
            "name": "id",
            "in": "path",
            "required": true,
            "schema": {
              "type": "integer",
              "format": "int32"
            }
          }
        ],
        "requestBody": {
          "content": {
            "application/json": {
              "schema": {
                "$ref": "#/components/schemas/FamilyContactDto"
              }
            },
            "text/json": {
              "schema": {
                "$ref": "#/components/schemas/FamilyContactDto"
              }
            },
            "application/*+json": {
              "schema": {
                "$ref": "#/components/schemas/FamilyContactDto"
              }
            }
          }
        },
        "responses": {
          "200": {
            "description": "OK"
          }
        }
      },
      "delete": {
        "tags": [
          "FamilyContact"
        ],
        "parameters": [
          {
            "name": "id",
            "in": "path",
            "required": true,
            "schema": {
              "type": "integer",
              "format": "int32"
            }
          }
        ],
        "responses": {
          "200": {
            "description": "OK"
          }
        }
      }
    },
    "/api/student/payments/pay/{feeId}": {
      "post": {
        "tags": [
          "FeePayment"
        ],
        "parameters": [
          {
            "name": "feeId",
            "in": "path",
            "required": true,
            "schema": {
              "type": "integer",
              "format": "int32"
            }
          }
        ],
        "requestBody": {
          "content": {
            "application/json": {
              "schema": {
                "$ref": "#/components/schemas/FeePaymentDto"
              }
            },
            "text/json": {
              "schema": {
                "$ref": "#/components/schemas/FeePaymentDto"
              }
            },
            "application/*+json": {
              "schema": {
                "$ref": "#/components/schemas/FeePaymentDto"
              }
            }
          }
        },
        "responses": {
          "200": {
            "description": "OK"
          }
        }
      }
    },
    "/api/Fees": {
      "get": {
        "tags": [
          "Fees"
        ],
        "responses": {
          "200": {
            "description": "OK"
          }
        }
      },
      "post": {
        "tags": [
          "Fees"
        ],
        "requestBody": {
          "content": {
            "application/json": {
              "schema": {
                "$ref": "#/components/schemas/FeesDto"
              }
            },
            "text/json": {
              "schema": {
                "$ref": "#/components/schemas/FeesDto"
              }
            },
            "application/*+json": {
              "schema": {
                "$ref": "#/components/schemas/FeesDto"
              }
            }
          }
        },
        "responses": {
          "200": {
            "description": "OK"
          }
        }
      }
    },
    "/api/Fees/{id}": {
      "get": {
        "tags": [
          "Fees"
        ],
        "parameters": [
          {
            "name": "id",
            "in": "path",
            "required": true,
            "schema": {
              "type": "integer",
              "format": "int32"
            }
          }
        ],
        "responses": {
          "200": {
            "description": "OK"
          }
        }
      },
      "put": {
        "tags": [
          "Fees"
        ],
        "parameters": [
          {
            "name": "id",
            "in": "path",
            "required": true,
            "schema": {
              "type": "integer",
              "format": "int32"
            }
          }
        ],
        "requestBody": {
          "content": {
            "application/json": {
              "schema": {
                "$ref": "#/components/schemas/FeesDto"
              }
            },
            "text/json": {
              "schema": {
                "$ref": "#/components/schemas/FeesDto"
              }
            },
            "application/*+json": {
              "schema": {
                "$ref": "#/components/schemas/FeesDto"
              }
            }
          }
        },
        "responses": {
          "200": {
            "description": "OK"
          }
        }
      },
      "delete": {
        "tags": [
          "Fees"
        ],
        "parameters": [
          {
            "name": "id",
            "in": "path",
            "required": true,
            "schema": {
              "type": "integer",
              "format": "int32"
            }
          }
        ],
        "responses": {
          "200": {
            "description": "OK"
          }
        }
      }
    },
    "/api/Reports/summary": {
      "get": {
        "tags": [
          "Reports"
        ],
        "responses": {
          "200": {
            "description": "OK"
          }
        }
      }
    },
    "/api/Room": {
      "get": {
        "tags": [
          "Room"
        ],
        "responses": {
          "200": {
            "description": "OK"
          }
        }
      },
      "post": {
        "tags": [
          "Room"
        ],
        "requestBody": {
          "content": {
            "application/json": {
              "schema": {
                "$ref": "#/components/schemas/RoomDto"
              }
            },
            "text/json": {
              "schema": {
                "$ref": "#/components/schemas/RoomDto"
              }
            },
            "application/*+json": {
              "schema": {
                "$ref": "#/components/schemas/RoomDto"
              }
            }
          }
        },
        "responses": {
          "200": {
            "description": "OK"
          }
        }
      }
    },
    "/api/Room/{id}": {
      "get": {
        "tags": [
          "Room"
        ],
        "parameters": [
          {
            "name": "id",
            "in": "path",
            "required": true,
            "schema": {
              "type": "integer",
              "format": "int32"
            }
          }
        ],
        "responses": {
          "200": {
            "description": "OK"
          }
        }
      },
      "put": {
        "tags": [
          "Room"
        ],
        "parameters": [
          {
            "name": "id",
            "in": "path",
            "required": true,
            "schema": {
              "type": "integer",
              "format": "int32"
            }
          }
        ],
        "requestBody": {
          "content": {
            "application/json": {
              "schema": {
                "$ref": "#/components/schemas/RoomDto"
              }
            },
            "text/json": {
              "schema": {
                "$ref": "#/components/schemas/RoomDto"
              }
            },
            "application/*+json": {
              "schema": {
                "$ref": "#/components/schemas/RoomDto"
              }
            }
          }
        },
        "responses": {
          "200": {
            "description": "OK"
          }
        }
      },
      "delete": {
        "tags": [
          "Room"
        ],
        "parameters": [
          {
            "name": "id",
            "in": "path",
            "required": true,
            "schema": {
              "type": "integer",
              "format": "int32"
            }
          }
        ],
        "responses": {
          "200": {
            "description": "OK"
          }
        }
      }
    },
    "/api/RoomAssignment/assign": {
      "post": {
        "tags": [
          "RoomAssignment"
        ],
        "parameters": [
          {
            "name": "studentId",
            "in": "query",
            "schema": {
              "type": "integer",
              "format": "int32"
            }
          },
          {
            "name": "roomId",
            "in": "query",
            "schema": {
              "type": "integer",
              "format": "int32"
            }
          }
        ],
        "responses": {
          "200": {
            "description": "OK"
          }
        }
      }
    },
    "/api/RoomAssignment/{id}": {
      "delete": {
        "tags": [
          "RoomAssignment"
        ],
        "parameters": [
          {
            "name": "id",
            "in": "path",
            "required": true,
            "schema": {
              "type": "integer",
              "format": "int32"
            }
          }
        ],
        "responses": {
          "200": {
            "description": "OK"
          }
        }
      }
    },
    "/api/SecondaryEducation": {
      "get": {
        "tags": [
          "SecondaryEducation"
        ],
        "responses": {
          "200": {
            "description": "OK"
          }
        }
      },
      "post": {
        "tags": [
          "SecondaryEducation"
        ],
        "requestBody": {
          "content": {
            "application/json": {
              "schema": {
                "$ref": "#/components/schemas/SecondaryEducationDto"
              }
            },
            "text/json": {
              "schema": {
                "$ref": "#/components/schemas/SecondaryEducationDto"
              }
            },
            "application/*+json": {
              "schema": {
                "$ref": "#/components/schemas/SecondaryEducationDto"
              }
            }
          }
        },
        "responses": {
          "200": {
            "description": "OK"
          }
        }
      }
    },
    "/api/SecondaryEducation/{studentId}": {
      "get": {
        "tags": [
          "SecondaryEducation"
        ],
        "parameters": [
          {
            "name": "studentId",
            "in": "path",
            "required": true,
            "schema": {
              "type": "integer",
              "format": "int32"
            }
          }
        ],
        "responses": {
          "200": {
            "description": "OK"
          }
        }
      },
      "put": {
        "tags": [
          "SecondaryEducation"
        ],
        "parameters": [
          {
            "name": "studentId",
            "in": "path",
            "required": true,
            "schema": {
              "type": "integer",
              "format": "int32"
            }
          }
        ],
        "requestBody": {
          "content": {
            "application/json": {
              "schema": {
                "$ref": "#/components/schemas/SecondaryEducationDto"
              }
            },
            "text/json": {
              "schema": {
                "$ref": "#/components/schemas/SecondaryEducationDto"
              }
            },
            "application/*+json": {
              "schema": {
                "$ref": "#/components/schemas/SecondaryEducationDto"
              }
            }
          }
        },
        "responses": {
          "200": {
            "description": "OK"
          }
        }
      },
      "delete": {
        "tags": [
          "SecondaryEducation"
        ],
        "parameters": [
          {
            "name": "studentId",
            "in": "path",
            "required": true,
            "schema": {
              "type": "integer",
              "format": "int32"
            }
          }
        ],
        "responses": {
          "200": {
            "description": "OK"
          }
        }
      }
    },
    "/api/Student": {
      "get": {
        "tags": [
          "Student"
        ],
        "responses": {
          "200": {
            "description": "OK"
          }
        }
      },
      "post": {
        "tags": [
          "Student"
        ],
        "requestBody": {
          "content": {
            "application/json": {
              "schema": {
                "$ref": "#/components/schemas/StudentDto"
              }
            },
            "text/json": {
              "schema": {
                "$ref": "#/components/schemas/StudentDto"
              }
            },
            "application/*+json": {
              "schema": {
                "$ref": "#/components/schemas/StudentDto"
              }
            }
          }
        },
        "responses": {
          "200": {
            "description": "OK"
          }
        }
      }
    },
    "/api/Student/{id}": {
      "get": {
        "tags": [
          "Student"
        ],
        "parameters": [
          {
            "name": "id",
            "in": "path",
            "required": true,
            "schema": {
              "type": "integer",
              "format": "int32"
            }
          }
        ],
        "responses": {
          "200": {
            "description": "OK"
          }
        }
      },
      "put": {
        "tags": [
          "Student"
        ],
        "parameters": [
          {
            "name": "id",
            "in": "path",
            "required": true,
            "schema": {
              "type": "integer",
              "format": "int32"
            }
          }
        ],
        "requestBody": {
          "content": {
            "application/json": {
              "schema": {
                "$ref": "#/components/schemas/StudentDto"
              }
            },
            "text/json": {
              "schema": {
                "$ref": "#/components/schemas/StudentDto"
              }
            },
            "application/*+json": {
              "schema": {
                "$ref": "#/components/schemas/StudentDto"
              }
            }
          }
        },
        "responses": {
          "200": {
            "description": "OK"
          }
        }
      },
      "delete": {
        "tags": [
          "Student"
        ],
        "parameters": [
          {
            "name": "id",
            "in": "path",
            "required": true,
            "schema": {
              "type": "integer",
              "format": "int32"
            }
          }
        ],
        "responses": {
          "200": {
            "description": "OK"
          }
        }
      }
    },
    "/api/Student/self-update": {
      "put": {
        "tags": [
          "Student"
        ],
        "requestBody": {
          "content": {
            "application/json": {
              "schema": {
                "$ref": "#/components/schemas/StudentDto"
              }
            },
            "text/json": {
              "schema": {
                "$ref": "#/components/schemas/StudentDto"
              }
            },
            "application/*+json": {
              "schema": {
                "$ref": "#/components/schemas/StudentDto"
              }
            }
          }
        },
        "responses": {
          "200": {
            "description": "OK"
          }
        }
      }
    },
    "/api/student/applications/submit": {
      "post": {
        "tags": [
          "StudentApplications"
        ],
        "requestBody": {
          "content": {
            "application/json": {
              "schema": {
                "$ref": "#/components/schemas/FullFormDto"
              }
            },
            "text/json": {
              "schema": {
                "$ref": "#/components/schemas/FullFormDto"
              }
            },
            "application/*+json": {
              "schema": {
                "$ref": "#/components/schemas/FullFormDto"
              }
            }
          }
        },
        "responses": {
          "200": {
            "description": "OK"
          }
        }
      }
    },
    "/api/student/applications/my-applications": {
      "get": {
        "tags": [
          "StudentApplications"
        ],
        "responses": {
          "200": {
            "description": "OK"
          }
        }
      }
    },
    "/api/student/auth/register": {
      "post": {
        "tags": [
          "StudentAuth"
        ],
        "requestBody": {
          "content": {
            "application/json": {
              "schema": {
                "$ref": "#/components/schemas/RegisterDto"
              }
            },
            "text/json": {
              "schema": {
                "$ref": "#/components/schemas/RegisterDto"
              }
            },
            "application/*+json": {
              "schema": {
                "$ref": "#/components/schemas/RegisterDto"
              }
            }
          }
        },
        "responses": {
          "200": {
            "description": "OK"
          }
        }
      }
    },
    "/api/student/auth/login": {
      "post": {
        "tags": [
          "StudentAuth"
        ],
        "requestBody": {
          "content": {
            "application/json": {
              "schema": {
                "$ref": "#/components/schemas/LoginDto"
              }
            },
            "text/json": {
              "schema": {
                "$ref": "#/components/schemas/LoginDto"
              }
            },
            "application/*+json": {
              "schema": {
                "$ref": "#/components/schemas/LoginDto"
              }
            }
          }
        },
        "responses": {
          "200": {
            "description": "OK"
          }
        }
      }
    },
    "/api/student/complaints/submit": {
      "post": {
        "tags": [
          "StudentComplaints"
        ],
        "requestBody": {
          "content": {
            "application/json": {
              "schema": {
                "$ref": "#/components/schemas/SubmitComplaintDto"
              }
            },
            "text/json": {
              "schema": {
                "$ref": "#/components/schemas/SubmitComplaintDto"
              }
            },
            "application/*+json": {
              "schema": {
                "$ref": "#/components/schemas/SubmitComplaintDto"
              }
            }
          }
        },
        "responses": {
          "200": {
            "description": "OK"
          }
        }
      }
    },
    "/api/student/profile/notifications": {
      "get": {
        "tags": [
          "StudentProfile"
        ],
        "responses": {
          "200": {
            "description": "OK"
          }
        }
      }
    },
    "/api/student/profile/notifications/{id}/read": {
      "put": {
        "tags": [
          "StudentProfile"
        ],
        "parameters": [
          {
            "name": "id",
            "in": "path",
            "required": true,
            "schema": {
              "type": "integer",
              "format": "int32"
            }
          }
        ],
        "responses": {
          "200": {
            "description": "OK"
          }
        }
      }
    },
    "/api/student/profile/fees": {
      "get": {
        "tags": [
          "StudentProfile"
        ],
        "responses": {
          "200": {
            "description": "OK"
          }
        }
      }
    },
    "/api/student/profile/assignments": {
      "get": {
        "tags": [
          "StudentProfile"
        ],
        "responses": {
          "200": {
            "description": "OK"
          }
        }
      }
    },
    "/api/student/profile/details": {
      "get": {
        "tags": [
          "StudentProfile"
        ],
        "responses": {
          "200": {
            "description": "OK"
          }
        }
      }
    },
    "/api/users/{id}": {
      "delete": {
        "tags": [
          "User"
        ],
        "parameters": [
          {
            "name": "id",
            "in": "path",
            "required": true,
            "schema": {
              "type": "integer",
              "format": "int32"
            }
          }
        ],
        "responses": {
          "200": {
            "description": "OK"
          }
        }
      }
    }
  },
  "components": {
    "schemas": {
      "AcademicEducationDto": {
        "type": "object",
        "properties": {
          "studentId": {
            "type": "integer",
            "format": "int32"
          },
          "currentGPA": {
            "type": "number",
            "format": "double"
          },
          "lastYearGrade": {
            "type": "string",
            "nullable": true
          }
        },
        "additionalProperties": false
      },
      "ApplicationStatusDto": {
        "type": "object",
        "properties": {
          "statusId": {
            "type": "integer",
            "format": "int32"
          },
          "label": {
            "type": "string",
            "nullable": true
          },
          "colorCode": {
            "type": "string",
            "nullable": true
          },
          "description": {
            "type": "string",
            "nullable": true
          }
        },
        "additionalProperties": false
      },
      "ApplicationWindowDto": {
        "type": "object",
        "properties": {
          "windowId": {
            "type": "integer",
            "format": "int32"
          },
          "title": {
            "type": "string",
            "nullable": true
          },
          "description": {
            "type": "string",
            "nullable": true
          },
          "createdAt": {
            "type": "string",
            "format": "date-time"
          },
          "startDate": {
            "type": "string",
            "format": "date-time"
          },
          "endDate": {
            "type": "string",
            "format": "date-time"
          },
          "status": {
            "type": "string",
            "nullable": true
          },
          "userId": {
            "type": "integer",
            "format": "int32"
          }
        },
        "additionalProperties": false
      },
      "BuildingDto": {
        "type": "object",
        "properties": {
          "buildingId": {
            "type": "integer",
            "format": "int32"
          },
          "name": {
            "type": "string",
            "nullable": true
          },
          "type": {
            "type": "string",
            "nullable": true
          },
          "numberOfFloors": {
            "type": "integer",
            "format": "int32"
          },
          "status": {
            "type": "string",
            "nullable": true
          }
        },
        "additionalProperties": false
      },
      "FamilyContactDto": {
        "type": "object",
        "properties": {
          "contactId": {
            "type": "integer",
            "format": "int32"
          },
          "fullName": {
            "type": "string",
            "nullable": true
          },
          "nationalId": {
            "type": "string",
            "nullable": true
          },
          "relation": {
            "type": "string",
            "nullable": true
          },
          "job": {
            "type": "string",
            "nullable": true
          },
          "phoneNumber": {
            "type": "string",
            "nullable": true
          },
          "address": {
            "type": "string",
            "nullable": true
          }
        },
        "additionalProperties": false
      },
      "FeePaymentDto": {
        "type": "object",
        "properties": {
          "studentId": {
            "type": "integer",
            "format": "int32"
          },
          "transactionCode": {
            "type": "string",
            "nullable": true
          },
          "receiptFilePath": {
            "type": "string",
            "nullable": true
          }
        },
        "additionalProperties": false
      },
      "FeesDto": {
        "type": "object",
        "properties": {
          "feeId": {
            "type": "integer",
            "format": "int32"
          },
          "amount": {
            "type": "number",
            "format": "double"
          },
          "feeType": {
            "type": "string",
            "nullable": true
          },
          "status": {
            "type": "string",
            "nullable": true
          },
          "createdAt": {
            "type": "string",
            "format": "date-time"
          },
          "studentId": {
            "type": "integer",
            "format": "int32"
          },
          "userId": {
            "type": "integer",
            "format": "int32"
          },
          "assignmentId": {
            "type": "integer",
            "format": "int32",
            "nullable": true
          }
        },
        "additionalProperties": false
      },
      "FullFormDto": {
        "type": "object",
        "properties": {
          "studentType": {
            "$ref": "#/components/schemas/StudentTypeEnum"
          },
          "studentInfo": {
            "$ref": "#/components/schemas/StudentDto"
          },
          "fatherInfo": {
            "$ref": "#/components/schemas/FamilyContactDto"
          },
          "selectedGuardianRelation": {
            "type": "string",
            "nullable": true
          },
          "otherGuardianInfo": {
            "$ref": "#/components/schemas/FamilyContactDto"
          },
          "secondaryInfo": {
            "$ref": "#/components/schemas/SecondaryEducationDto"
          },
          "academicInfo": {
            "$ref": "#/components/schemas/AcademicEducationDto"
          }
        },
        "additionalProperties": false
      },
      "LoginDto": {
        "required": [
          "password",
          "username"
        ],
        "type": "object",
        "properties": {
          "username": {
            "maxLength": 50,
            "minLength": 1,
            "type": "string"
          },
          "password": {
            "minLength": 6,
            "type": "string"
          }
        },
        "additionalProperties": false
      },
      "NotificationDto": {
        "type": "object",
        "properties": {
          "notificationId": {
            "type": "integer",
            "format": "int32"
          },
          "title": {
            "type": "string",
            "nullable": true
          },
          "message": {
            "type": "string",
            "nullable": true
          },
          "createdAt": {
            "type": "string",
            "format": "date-time"
          },
          "isRead": {
            "type": "boolean"
          },
          "studentId": {
            "type": "integer",
            "format": "int32"
          },
          "userId": {
            "type": "integer",
            "format": "int32",
            "nullable": true
          },
          "applicationId": {
            "type": "integer",
            "format": "int32",
            "nullable": true
          }
        },
        "additionalProperties": false
      },
      "RegisterDto": {
        "required": [
          "password",
          "role",
          "userName"
        ],
        "type": "object",
        "properties": {
          "userName": {
            "minLength": 1,
            "type": "string"
          },
          "password": {
            "minLength": 1,
            "type": "string"
          },
          "role": {
            "minLength": 1,
            "type": "string"
          },
          "studentId": {
            "type": "integer",
            "format": "int32",
            "nullable": true
          }
        },
        "additionalProperties": false
      },
      "ResolveComplaintDto": {
        "required": [
          "resolutionMessage"
        ],
        "type": "object",
        "properties": {
          "resolutionMessage": {
            "minLength": 1,
            "type": "string"
          }
        },
        "additionalProperties": false
      },
      "RoomDto": {
        "type": "object",
        "properties": {
          "roomId": {
            "type": "integer",
            "format": "int32"
          },
          "roomNumber": {
            "type": "string",
            "nullable": true
          },
          "capacity": {
            "type": "integer",
            "format": "int32"
          },
          "currentOccupancy": {
            "type": "integer",
            "format": "int32"
          },
          "buildingId": {
            "type": "integer",
            "format": "int32"
          },
          "apartmentName": {
            "type": "string",
            "nullable": true
          },
          "status": {
            "type": "integer",
            "format": "int32"
          }
        },
        "additionalProperties": false
      },
      "SecondaryEducationDto": {
        "type": "object",
        "properties": {
          "studentId": {
            "type": "integer",
            "format": "int32"
          },
          "secondaryStream": {
            "type": "string",
            "nullable": true
          },
          "totalScore": {
            "type": "number",
            "format": "double"
          },
          "percentage": {
            "type": "number",
            "format": "double"
          },
          "grade": {
            "type": "string",
            "nullable": true
          }
        },
        "additionalProperties": false
      },
      "StudentDto": {
        "type": "object",
        "properties": {
          "studentId": {
            "type": "integer",
            "format": "int32"
          },
          "nationalId": {
            "type": "string",
            "nullable": true
          },
          "fullName": {
            "type": "string",
            "nullable": true
          },
          "studentType": {
            "$ref": "#/components/schemas/StudentTypeEnum"
          },
          "birthDate": {
            "type": "string",
            "format": "date-time"
          },
          "birthPlace": {
            "type": "string",
            "nullable": true
          },
          "gender": {
            "type": "string",
            "nullable": true
          },
          "religion": {
            "type": "string",
            "nullable": true
          },
          "governorate": {
            "type": "string",
            "nullable": true
          },
          "city": {
            "type": "string",
            "nullable": true
          },
          "address": {
            "type": "string",
            "nullable": true
          },
          "email": {
            "type": "string",
            "nullable": true
          },
          "phone": {
            "type": "string",
            "nullable": true
          },
          "faculty": {
            "type": "string",
            "nullable": true
          },
          "department": {
            "type": "string",
            "nullable": true
          },
          "level": {
            "type": "string",
            "nullable": true
          },
          "fatherContactId": {
            "type": "integer",
            "format": "int32"
          },
          "guardianContactId": {
            "type": "integer",
            "format": "int32"
          },
          "userId": {
            "type": "integer",
            "format": "int32"
          }
        },
        "additionalProperties": false
      },
      "StudentTypeEnum": {
        "enum": [
          0,
          1
        ],
        "type": "integer",
        "format": "int32"
      },
      "SubmitComplaintDto": {
        "required": [
          "message",
          "title"
        ],
        "type": "object",
        "properties": {
          "title": {
            "maxLength": 100,
            "minLength": 0,
            "type": "string"
          },
          "message": {
            "maxLength": 500,
            "minLength": 0,
            "type": "string"
          }
        },
        "additionalProperties": false
      }
    },
    "securitySchemes": {
      "Bearer": {
        "type": "apiKey",
        "description": "Enter 'Bearer {token}'",
        "name": "Authorization",
        "in": "header"
      }
    }
  },
  "security": [
    {
      "Bearer": []
    }
  ]
}